notifly/__init__.py
notifly/discord.py
notifly/gpu_stats.py
notifly/slack.py
notifly/telegram.py
notifly/tf_notifier.py
notifly-1.3.3.dist-info/LICENSE
notifly-1.3.3.dist-info/METADATA
notifly-1.3.3.dist-info/WHEEL
notifly-1.3.3.dist-info/top_level.txt
notifly-1.3.3.dist-info/RECORD
