Metadata-Version: 2.1
Name: notifly
Version: 1.3.3
Summary: Notification on the fly !
Home-page: https://github.com/rexdivakar/Telegram-Notifly
Author: Divakar R, Sanchit Jain
Author-email: rexdivakar@hotmail.com , sanchitjain1996@gmail.com
License: MIT
Keywords: Bot Notification
Classifier: Development Status :: 5 - Production/Stable
Classifier: Intended Audience :: Education
Classifier: Operating System :: Microsoft :: Windows :: Windows 10
Classifier: License :: OSI Approved :: MIT License
Classifier: Programming Language :: Python :: 3
License-File: LICENSE
Requires-Dist: requests
Requires-Dist: numpy ==1.19.3
Requires-Dist: matplotlib
Requires-Dist: slackclient
Requires-Dist: python-dotenv
Requires-Dist: psutil
